{
  "$schema": "https://pocket-stack.dev/schema/pocket-2.json",
  "pocket": 2,
  "id": "dev.pocket-stack.hero",
  "name": "pocketjs-hero",
  "title": "PocketJS Hero",
  "version": "0.4.0",
  "engine": {
    "capabilities": {
      "requires": [
        "text.glyphs.baked",
        "input.buttons",
        "input.analog.left"
      ]
    }
  },
  "app": {
    "entry": "demos/hero/main.tsx",
    "output": "hero-main",
    "framework": "solid",
    "viewport": {
      "logical": [480, 272],
      "presentation": "integer-fit"
    }
  }
}
